flotorch_core/__init__.py
flotorch_core/chunking/__init__.py
flotorch_core/chunking/chunking.py
flotorch_core/chunking/chunking_provider_factory.py
flotorch_core/chunking/fixedsize_chunking.py
flotorch_core/chunking/hierarical_chunking.py
flotorch_core/config/config.py
flotorch_core/config/config_provider.py
flotorch_core/config/env_config_provider.py
flotorch_core/embedding/__init__.py
flotorch_core/embedding/bedrock_embedding.py
flotorch_core/embedding/bge_large_embedding.py
flotorch_core/embedding/cohere_embedding.py
flotorch_core/embedding/embedding.py
flotorch_core/embedding/embedding_registry.py
flotorch_core/embedding/gateway_embedding.py
flotorch_core/embedding/llama_embedding.py
flotorch_core/embedding/sagemaker_embedding.py
flotorch_core/embedding/titanv1_embedding.py
flotorch_core/embedding/titanv2_embedding.py
flotorch_core/embedding/guardrails/__init__.py
flotorch_core/embedding/guardrails/guardrail_config.py
flotorch_core/embedding/guardrails/guardrails_embedding.py
flotorch_core/evaluator/base_evaluator.py
flotorch_core/evaluator/deepeval_evaluator.py
flotorch_core/evaluator/evaluation_item.py
flotorch_core/evaluator/ragas_evaluator.py
flotorch_core/evaluator/metrics/base_metrics.py
flotorch_core/evaluator/metrics/metrics_keys.py
flotorch_core/evaluator/metrics/deepeval_metrics/deepeval_metrics.py
flotorch_core/evaluator/metrics/ragas_metrics/ragas_metrics.py
flotorch_core/guardrails/__init__.py
flotorch_core/guardrails/guardrails.py
flotorch_core/inferencer/__init__.py
flotorch_core/inferencer/bedrock_inferencer.py
flotorch_core/inferencer/gateway_inferencer.py
flotorch_core/inferencer/inferencer.py
flotorch_core/inferencer/inferencer_provider_factory.py
flotorch_core/inferencer/llama_inferencer.py
flotorch_core/inferencer/sagemaker_inferencer.py
flotorch_core/inferencer/guardrails/guardrails_inferencer.py
flotorch_core/logger/__init__.py
flotorch_core/logger/console_logger_provider.py
flotorch_core/logger/global_logger.py
flotorch_core-2.10.0.dist-info/licenses/LICENSE
flotorch_core-2.10.0.dist-info/METADATA
flotorch_core-2.10.0.dist-info/WHEEL
flotorch_core-2.10.0.dist-info/top_level.txt
flotorch_core-2.10.0.dist-info/RECORD
